refiner/__init__.py
refiner/embeddings.py
refiner/loaders.py
refiner/transformers.py
refiner/integrations/__init__.py
refiner/integrations/refiner_langchain.py
refiner/integrations/refiner_openai.py
refiner/integrations/refiner_pinecone.py
refiner-0.0.7.dist-info/LICENSE
refiner-0.0.7.dist-info/METADATA
refiner-0.0.7.dist-info/WHEEL
refiner-0.0.7.dist-info/top_level.txt
refiner-0.0.7.dist-info/RECORD
