Metadata-Version: 2.1
Name: refiner
Version: 0.0.7
Summary: Refiner is a python package that allows you to store text as vectors in Pinecone and then search for similar text. It uses OpenAI to generate embeddings and then uses Pinecone to store and search for similar text.
Author-email: Alex Daro <gmx2267@gmail.com>
Project-URL: Homepage, https://github.com/adaro/ai-refiner
Classifier: Programming Language :: Python :: 3
Classifier: License :: OSI Approved :: MIT License
Classifier: Operating System :: OS Independent
Requires-Python: >=3.7
License-File: LICENSE
Requires-Dist: click
Requires-Dist: matplotlib
Requires-Dist: openai
Requires-Dist: pandas
Requires-Dist: pinecone-client
Requires-Dist: plotly
Requires-Dist: python-dotenv
Requires-Dist: scipy
Requires-Dist: scikit-learn
Requires-Dist: langchain
Requires-Dist: bs4
